SDPA-OFDM/__init__.py
SDPA-OFDM/modulations.py
SDPA-OFDM/ofdm_modulator.py
SDPA_OFDM/__init__.py
SDPA_OFDM/modulations.py
SDPA_OFDM/modulator.py
SDPA_OFDM/ofdm_modulator.py
SDPA_OFDM/pn9.py
SDPA_OFDM-1.0.0.dist-info/METADATA
SDPA_OFDM-1.0.0.dist-info/WHEEL
SDPA_OFDM-1.0.0.dist-info/top_level.txt
SDPA_OFDM-1.0.0.dist-info/RECORD
